Oregano-4.4.2.data/scripts/oregano-app
home/karol/.local/share/applications/oregano.desktop
home/karol/.local/share/icons/hicolor/256x256/apps/oregano.png
home/karol/.local/share/icons/hicolor/scaleable/apps/oregano.svg
home/karol/.local/share/metainfo/org.oregano.Oregano.appdata.xml
home/karol/.local/share/pixmaps/oregano.png
oregano/__init__.py
oregano/address.py
oregano/asert_daa.py
oregano/base_wizard.py
oregano/bitcoin.py
oregano/blockchain.py
oregano/caches.py
oregano/cashacct.py
oregano/cashaddr.py
oregano/coinchooser.py
oregano/commands.py
oregano/contacts.py
oregano/currencies.json
oregano/daemon.py
oregano/dnssec.py
oregano/ecc_fast.py
oregano/exchange_rate.py
oregano/i18n.py
oregano/interface.py
oregano/jsonrpc.py
oregano/keystore.py
oregano/libsecp256k1.so.0
oregano/libzbar.so.0
oregano/mnemonic.py
oregano/msqr.py
oregano/network.py
oregano/networks.py
oregano/old_contacts.py
oregano/old_mnemonic.py
oregano/paymentrequest.py
oregano/paymentrequest_pb2.py
oregano/pem.py
oregano/plot.py
oregano/plugins.py
oregano/ripemd.py
oregano/rsakey.py
oregano/schnorr.py
oregano/secp256k1.py
oregano/servers.json
oregano/servers_scalenet.json
oregano/servers_taxcoin.json
oregano/servers_testnet.json
oregano/servers_testnet4.json
oregano/simple_config.py
oregano/storage.py
oregano/synchronizer.py
oregano/transaction.py
oregano/util.py
oregano/verifier.py
oregano/version.py
oregano/wallet.py
oregano/web.py
oregano/websockets.py
oregano/winconsole.py
oregano/x509.py
oregano/qrreaders/__init__.py
oregano/qrreaders/abstract_base.py
oregano/qrreaders/osxqrdetect.py
oregano/qrreaders/zbar.py
oregano/slp/__init__.py
oregano/slp/exceptions.py
oregano/slp/slp.py
oregano/tor/__init__.py
oregano/tor/controller.py
oregano/tor/bin/tor
oregano/utils/__init__.py
oregano/utils/event.py
oregano/utils/macos.py
oregano/utils/unicode_tools.py
oregano/wordlist/chinese_simplified.txt
oregano/wordlist/english.txt
oregano/wordlist/japanese.txt
oregano/wordlist/portuguese.txt
Oregano-4.4.2.dist-info/AUTHORS
Oregano-4.4.2.dist-info/LICENCE
Oregano-4.4.2.dist-info/METADATA
Oregano-4.4.2.dist-info/WHEEL
Oregano-4.4.2.dist-info/top_level.txt
Oregano-4.4.2.dist-info/RECORD
