Metadata-Version: 2.1
Name: Oregano
Version: 4.4.2
Summary: Lightweight Ergon Wallet
Home-page: http://ergon.moe
Author: The Oregano Developers
Author-email: licho@ergon.moe
License: MIT Licence
License-File: LICENCE
License-File: AUTHORS
Requires-Dist: pyaes (>=0.1a1)
Requires-Dist: ecdsa (>=0.9)
Requires-Dist: requests
Requires-Dist: qrcode
Requires-Dist: protobuf (>=3.7.1)
Requires-Dist: jsonrpclib-pelix
Requires-Dist: PySocks (>=1.6.6)
Requires-Dist: qdarkstyle (>=2.8)
Requires-Dist: python-dateutil (<2.9)
Requires-Dist: stem (>=1.8.0)
Requires-Dist: certifi
Requires-Dist: pathvalidate
Requires-Dist: dnspython (>=2.0)
Provides-Extra: all
Requires-Dist: Cython (>=0.27) ; extra == 'all'
Requires-Dist: trezor[hidapi] (>=0.12.0) ; extra == 'all'
Requires-Dist: keepkey (>=6.1) ; extra == 'all'
Requires-Dist: btchip-python ; extra == 'all'
Requires-Dist: hidapi ; extra == 'all'
Requires-Dist: pyscard (>=2.0.0) ; extra == 'all'
Requires-Dist: pysatochip (>=0.11.4) ; extra == 'all'
Requires-Dist: PyQt5 (>=5.12.3) ; extra == 'all'
Requires-Dist: pycryptodomex ; extra == 'all'
Requires-Dist: psutil ; extra == 'all'
Requires-Dist: cryptography (>=2.6) ; extra == 'all'
Provides-Extra: gui
Requires-Dist: PyQt5 (>=5.12.3) ; extra == 'gui'
Requires-Dist: pycryptodomex ; extra == 'gui'
Requires-Dist: psutil ; extra == 'gui'
Requires-Dist: cryptography (>=2.6) ; extra == 'gui'
Provides-Extra: hardware
Requires-Dist: Cython (>=0.27) ; extra == 'hardware'
Requires-Dist: trezor[hidapi] (>=0.12.0) ; extra == 'hardware'
Requires-Dist: keepkey (>=6.1) ; extra == 'hardware'
Requires-Dist: btchip-python ; extra == 'hardware'
Requires-Dist: hidapi ; extra == 'hardware'
Requires-Dist: pyscard (>=2.0.0) ; extra == 'hardware'
Requires-Dist: pysatochip (>=0.11.4) ; extra == 'hardware'
